activecampaign/__init__.py
activecampaign/activities.py
activecampaign/addresses.py
activecampaign/automations.py
activecampaign/brandings.py
activecampaign/campaigns.py
activecampaign/client.py
activecampaign/contacts.py
activecampaign/customobjects.py
activecampaign/dealActivities.py
activecampaign/deals.py
activecampaign/deepdataintegrations.py
activecampaign/emailActivities.py
activecampaign/events.py
activecampaign/exception.py
activecampaign/lists.py
activecampaign/messages.py
activecampaign/notes.py
activecampaign/tags.py
activecampaign/tasks.py
activecampaign/users.py
activecampaign/webhooks.py
activecampaign_python-1.0.10.dist-info/LICENSE
activecampaign_python-1.0.10.dist-info/METADATA
activecampaign_python-1.0.10.dist-info/WHEEL
activecampaign_python-1.0.10.dist-info/RECORD
